botoflow/__init__.py
botoflow/activity_retrying.py
botoflow/constants.py
botoflow/decorator_descriptors.py
botoflow/decorators.py
botoflow/exceptions.py
botoflow/logging_filters.py
botoflow/manual_activity_completion_client.py
botoflow/options.py
botoflow/swf_exceptions.py
botoflow/utils.py
botoflow/workflow_definition.py
botoflow/workflow_execution.py
botoflow/workflow_starting.py
botoflow/workflow_time.py
botoflow/context/__init__.py
botoflow/context/activity_context.py
botoflow/context/context_base.py
botoflow/context/decision_context.py
botoflow/context/start_workflow_context.py
botoflow/core/__init__.py
botoflow/core/async_context.py
botoflow/core/async_event_loop.py
botoflow/core/async_root_task_context.py
botoflow/core/async_task.py
botoflow/core/async_task_context.py
botoflow/core/async_traceback.py
botoflow/core/base_future.py
botoflow/core/decorators.py
botoflow/core/exceptions.py
botoflow/core/future.py
botoflow/core/utils.py
botoflow/data_converter/__init__.py
botoflow/data_converter/abstract_data_converter.py
botoflow/data_converter/json_data_converter.py
botoflow/data_converter/pickle_data_converter.py
botoflow/decider/__init__.py
botoflow/decider/activity_future.py
botoflow/decider/activity_task_handler.py
botoflow/decider/child_workflow_execution_handler.py
botoflow/decider/decider.py
botoflow/decider/decision_task_poller.py
botoflow/decider/external_workflow_handler.py
botoflow/decider/timer_handler.py
botoflow/decider/workflow_execution_handler.py
botoflow/decider/workflow_replayer.py
botoflow/decisions/__init__.py
botoflow/decisions/decision_bases.py
botoflow/decisions/decision_list.py
botoflow/decisions/decisions.py
botoflow/flow_types/__init__.py
botoflow/flow_types/activity_type.py
botoflow/flow_types/base_flow_type.py
botoflow/flow_types/signal_type.py
botoflow/flow_types/workflow_type.py
botoflow/history_events/__init__.py
botoflow/history_events/event_bases.py
botoflow-0.8.dist-info/DESCRIPTION.rst
botoflow-0.8.dist-info/METADATA
botoflow-0.8.dist-info/metadata.json
botoflow-0.8.dist-info/RECORD
botoflow-0.8.dist-info/top_level.txt
botoflow-0.8.dist-info/WHEEL
