Metadata-Version: 2.0
Name: botoflow
Version: 0.8
Summary: Botoflow is an asynchronous framework for Amazon SWF that helps you build SWF applications using Python
Home-page: https://github.com/boto/botoflow
Author: Amazon.com, Darjus Loktevic
Author-email: darjus@gmail.com
License: Apache License 2.0
Platform: UNKNOWN
Classifier: Development Status :: 4 - Beta
Classifier: Intended Audience :: Developers
Classifier: Intended Audience :: System Administrators
Classifier: Natural Language :: English
Classifier: License :: OSI Approved :: Apache Software License
Classifier: Programming Language :: Python
Classifier: Programming Language :: Python :: 2.7
Classifier: Programming Language :: Python :: 3
Classifier: Programming Language :: Python :: 3.4
Classifier: Programming Language :: Python :: 3.5
Requires-Dist: botocore (>=1.1.10)
Requires-Dist: six (>=1.2.0)
Requires-Dist: dill (>=0.2)
Requires-Dist: retrying (>=1.3.3)
